{
  "execution_info": {
    "duration_ms": 1
  },
  "performance": {
    "final_balance": 99.98510316710355,
    "losing_trades": 1,
    "max_drawdown": 0.0003616020112908087,
    "profit_factor": 0.588119966398622,
    "risk_reward_ratio": 0.588119966398622,
    "sharpe_ratio": 0.0,
    "sortino_ratio": 0.0,
    "total_profit": -0.01489683289645205,
    "total_trades": 2,
    "win_rate": 0.5,
    "winning_trades": 1
  },
  "strategy_config": {
    "fib_initial": 0.382,
    "fib_limit1": 0.0,
    "fib_limit2": 0.618,
    "fib_sl": 2.618,
    "fib_threshold": 3.0812781278127814,
    "fib_tp": 1.618,
    "initial_balance": 100.0,
    "leverage": 20.0,
    "max_risk_per_trade": 0.02,
    "min_signal_strength": 0.5,
    "name": "final_backtest",
    "pivot_lookback": 5,
    "signal_lookback": 1
  }
}