{
  "id": "34e700fa-f423-479c-ac50-a2b76ce38b67",
  "levels": {
    "entry_price": 406.546,
    "limit1_price": 417.13,
    "limit1_size": 0.0,
    "limit2_price": 420.562,
    "limit2_size": 0.0,
    "new_tp1": null,
    "new_tp2": null,
    "position_id": "cee8f327-40ad-4fc6-a51e-0d7810591513",
    "position_type": "Short",
    "risk_percent": 0.0,
    "size": 0.0,
    "status": "Pending",
    "stop_loss": 413.962,
    "take_profit": 391.714
  },
  "metadata": {
    "generator_version": "0.1.0",
    "test": false,
    "timestamp_ms": 1746676672077
  },
  "position_type": "SHORT",
  "price": 406.546,
  "processed": false,
  "reason": "Pivot high: 411.13, Pivot low: 399.13",
  "stop_loss": 413.962,
  "strength": 0.7999999999999999,
  "symbol": "BCH",
  "take_profit": 391.714,
  "timestamp": "2025-05-08T03:57:52.077450300+00:00"
}