{
  "id": "c2e3f6ab-9329-4a89-bfb5-ec91ed91bdba",
  "levels": {
    "entry_price": 99279.068,
    "limit1_price": 99302.0,
    "limit1_size": 0.0,
    "limit2_price": 99309.436,
    "limit2_size": 0.0,
    "new_tp1": null,
    "new_tp2": null,
    "position_id": "30ba163c-0a76-4463-8223-c0c473604caf",
    "position_type": "Short",
    "risk_percent": 0.0,
    "size": 0.0,
    "status": "Pending",
    "stop_loss": 99295.136,
    "take_profit": 99246.932
  },
  "metadata": {
    "generator_version": "0.1.0",
    "test": false,
    "timestamp_ms": 1746689529791
  },
  "position_type": "SHORT",
  "price": 99279.068,
  "processed": true,
  "reason": "Pivot high: 99289, Pivot low: 99263",
  "stop_loss": 99295.136,
  "strength": 0.7,
  "symbol": "BTC",
  "take_profit": 99246.932,
  "timestamp": "2025-05-08T07:32:09.791076100+00:00"
}