{
  "id": "58f33d72-11fd-4e06-8b0a-99277956b280",
  "levels": {
    "entry_price": 103305.496,
    "limit1_price": 103369.0,
    "limit1_size": 0.0,
    "limit2_price": 103389.592,
    "limit2_size": 0.0,
    "new_tp1": null,
    "new_tp2": null,
    "position_id": "a63145ed-4008-4ab9-95aa-e5a8b79ecb6e",
    "position_type": "Short",
    "risk_percent": 0.0,
    "size": 0.0,
    "status": "Pending",
    "stop_loss": 103349.992,
    "take_profit": 103216.504
  },
  "metadata": {
    "generator_version": "0.1.0",
    "test": false,
    "timestamp_ms": 1746748200348
  },
  "position_type": "SHORT",
  "price": 103305.496,
  "processed": false,
  "reason": "Pivot high: 103333, Pivot low: 103261",
  "stop_loss": 103349.992,
  "strength": 0.7,
  "symbol": "BTC",
  "take_profit": 103216.504,
  "timestamp": "2025-05-08T23:50:00.348879+00:00"
}